package_extras/__init__.py
package_extras-0.3.0.dist-info/WHEEL
package_extras-0.3.0.dist-info/METADATA
package_extras-0.3.0.dist-info/RECORD
